[
  { "title": "تملي معاك", "artist": "Amr Diab" },
  { "title": "كل القصايد", "artist": "Marwan Khoury" },
  { "title": "كيفك انت", "artist": "Fairuz" },
  { "title": "نسم علينا الهوى", "artist": "Fairuz" },
  { "title": "وحشتيني", "artist": "Amr Diab" },
  { "title": "يا غايب", "artist": "Fadel Shaker" },
  { "title": "بحبك وحشتيني", "artist": "Hussein Al Jasmi" },
  { "title": "أنا لك على طول", "artist": "Abdel Halim Hafez" },
  { "title": "جانا الهوى", "artist": "Abdel Halim Hafez" },
  { "title": "زيديني عشقا", "artist": "Kadim Al Sahir" }
  
]
